ezstorage/__init__.py
ezstorage/constants.py
ezstorage/table.py
ezstorage/providers/__init__.py
ezstorage/providers/__template__.py
ezstorage/providers/sqlite.py
ezstorage/tokenizer/__init__.py
ezstorage/tokenizer/token.py
ezstorage/tokenizer/tokenizer.py
ezstorage/tokenizer/types.py
ezstorages-0.0.12.dist-info/LICENSE
ezstorages-0.0.12.dist-info/METADATA
ezstorages-0.0.12.dist-info/WHEEL
ezstorages-0.0.12.dist-info/top_level.txt
ezstorages-0.0.12.dist-info/RECORD
