Metadata-Version: 2.1
Name: ezstorages
Version: 0.0.12
Summary: Easy storage handler
Author: Sau1707
License: MIT License
Requires-Python: >=3.8
License-File: LICENSE
